LICENSE.txt
README.md
setup.py
pythonPackageCodigofacilito/__init__.py
pythonPackageCodigofacilito/__main__.py
pythonPackageCodigofacilito/workshops.py
pythonPackageCodigofacilito.egg-info/PKG-INFO
pythonPackageCodigofacilito.egg-info/SOURCES.txt
pythonPackageCodigofacilito.egg-info/dependency_links.txt
pythonPackageCodigofacilito.egg-info/entry_points.txt
pythonPackageCodigofacilito.egg-info/requires.txt
pythonPackageCodigofacilito.egg-info/top_level.txt