Metadata-Version: 2.1
Name: pythonPackageCodigofacilito
Version: 0.0.2
Summary: Permite consumir un API de Codigo Facilito
Home-page: https://github.com/TaniaAlexBM/pythonPackage
Author: Alejandra Benítez
Author-email: alejandrabenitezmtz@gmail.com
License: MIT
Keywords: codigofacilito
Platform: UNKNOWN
Classifier: Development Status :: 3 - Alpha
Classifier: Intended Audience :: Developers
Classifier: Topic :: Software Development :: Build Tools
Classifier: License :: OSI Approved :: MIT License
Classifier: Programming Language :: Python :: 3
License-File: LICENSE.txt
